makexlsx/__init__.py
makexlsx/__main__.py
makexlsx/cli.py
makexlsx/xlsx.py
makexlsx-0.1.dist-info/LICENSE
makexlsx-0.1.dist-info/METADATA
makexlsx-0.1.dist-info/WHEEL
makexlsx-0.1.dist-info/entry_points.txt
makexlsx-0.1.dist-info/top_level.txt
makexlsx-0.1.dist-info/RECORD
