Metadata-Version: 2.1
Name: makexlsx
Version: 0.1
Summary: Make XLSX spreadsheet from tabular data files
Home-page: https://git.sr.ht/~zondo/makexlsx
Author: Glenn Hutchings
Author-email: zondo42@gmail.com
License: BSD
Download-URL: http://pypi.python.org/pypi/makexlsx
Platform: UNKNOWN
Classifier: Development Status :: 4 - Beta
Classifier: Environment :: Console
Classifier: Intended Audience :: End Users/Desktop
Classifier: License :: OSI Approved :: BSD License
Classifier: Operating System :: Microsoft :: Windows
Classifier: Operating System :: POSIX
Classifier: Programming Language :: Python :: 2.7
Classifier: Programming Language :: Python :: 3
Classifier: Topic :: Office/Business
Classifier: Topic :: Scientific/Engineering
Requires-Dist: tablib
Requires-Dist: xlsxwriter
